<?xml version="1.0" encoding="UTF-8"?>

<Questionnaire xmlns="http://hl7.org/fhir">
  <id value="qs1"/>
  <contained>
    <ValueSet>
      <id value="vs2"/>
      <url value="urn:uuid:5f0d34d4-ebc4-4da4-8ad5-8b554ebc7b9d"/>
      <name value="Type options for ProcedureRequest.bodySite[x]"/>
      <description value="Type options for ProcedureRequest.bodySite[x]"/>
      <status value="active"/>
      <expansion>
        <identifier value="urn:uuid:5fe30bd7-96f0-430a-8826-1bebe65e04a0"/>
        <timestamp value="2015-03-24T00:03:46+00:00"/>
        <contains>
          <system value="http://hl7.org/fhir/data-types"/>
          <code value="CodeableConcept"/>
          <display value="CodeableConcept"/>
        </contains>
        <contains>
          <system value="http://hl7.org/fhir/resource-types"/>
          <code value="BodySite"/>
          <display value="BodySite"/>
        </contains>
      </expansion>
    </ValueSet>
  </contained>
  <contained>
    <ValueSet>
      <id value="vs3"/>
      <url value="urn:uuid:8301babb-623e-44ef-b11e-78682f184113"/>
      <name value="Type options for ProcedureRequest.timing[x]"/>
      <description value="Type options for ProcedureRequest.timing[x]"/>
      <status value="active"/>
      <expansion>
        <identifier value="urn:uuid:80cfe5bb-a3e4-4a0c-9114-ebe61cd2c9ca"/>
        <timestamp value="2015-03-24T00:03:46+00:00"/>
        <contains>
          <system value="http://hl7.org/fhir/data-types"/>
          <code value="dateTime"/>
          <display value="dateTime"/>
        </contains>
        <contains>
          <system value="http://hl7.org/fhir/data-types"/>
          <code value="Period"/>
          <display value="Period"/>
        </contains>
        <contains>
          <system value="http://hl7.org/fhir/data-types"/>
          <code value="Timing"/>
          <display value="Timing"/>
        </contains>
      </expansion>
    </ValueSet>
  </contained>
  <contained>
    <ValueSet>
      <id value="vs4"/>
      <url value="urn:uuid:4219f84e-e172-40a5-8158-c8a267bc0525"/>
      <name value="Type options for ProcedureRequest.performer"/>
      <description value="Type options for ProcedureRequest.performer"/>
      <status value="active"/>
      <expansion>
        <identifier value="urn:uuid:ca0c8eba-3f82-49cd-b32f-ae011f1a1d9f"/>
        <timestamp value="2015-03-24T00:03:46+00:00"/>
        <contains>
          <system value="http://hl7.org/fhir/resource-types"/>
          <code value="Practitioner"/>
          <display value="Practitioner"/>
        </contains>
        <contains>
          <system value="http://hl7.org/fhir/resource-types"/>
          <code value="Organization"/>
          <display value="Organization"/>
        </contains>
        <contains>
          <system value="http://hl7.org/fhir/resource-types"/>
          <code value="Patient"/>
          <display value="Patient"/>
        </contains>
        <contains>
          <system value="http://hl7.org/fhir/resource-types"/>
          <code value="RelatedPerson"/>
          <display value="RelatedPerson"/>
        </contains>
      </expansion>
    </ValueSet>
  </contained>
  <contained>
    <ValueSet>
      <id value="vs5"/>
      <url value="urn:uuid:767cc0bb-f144-4c03-a9bf-fb89852b646c"/>
      <name value="Type options for ProcedureRequest.asNeeded[x]"/>
      <description value="Type options for ProcedureRequest.asNeeded[x]"/>
      <status value="active"/>
      <expansion>
        <identifier value="urn:uuid:b16cffbe-78fa-4791-b05c-81f4a2808f73"/>
        <timestamp value="2015-03-24T00:03:46+00:00"/>
        <contains>
          <system value="http://hl7.org/fhir/data-types"/>
          <code value="boolean"/>
          <display value="boolean"/>
        </contains>
        <contains>
          <system value="http://hl7.org/fhir/data-types"/>
          <code value="CodeableConcept"/>
          <display value="CodeableConcept"/>
        </contains>
      </expansion>
    </ValueSet>
  </contained>
  <contained>
    <ValueSet>
      <id value="vs6"/>
      <url value="urn:uuid:a8085935-af16-4ef5-839f-ea86cf3da19f"/>
      <name value="Type options for ProcedureRequest.orderer"/>
      <description value="Type options for ProcedureRequest.orderer"/>
      <status value="active"/>
      <expansion>
        <identifier value="urn:uuid:9b3121c6-b1ac-44ec-b13c-c537be4c342d"/>
        <timestamp value="2015-03-24T00:03:46+00:00"/>
        <contains>
          <system value="http://hl7.org/fhir/resource-types"/>
          <code value="Practitioner"/>
          <display value="Practitioner"/>
        </contains>
        <contains>
          <system value="http://hl7.org/fhir/resource-types"/>
          <code value="Patient"/>
          <display value="Patient"/>
        </contains>
        <contains>
          <system value="http://hl7.org/fhir/resource-types"/>
          <code value="RelatedPerson"/>
          <display value="RelatedPerson"/>
        </contains>
        <contains>
          <system value="http://hl7.org/fhir/resource-types"/>
          <code value="Device"/>
          <display value="Device"/>
        </contains>
      </expansion>
    </ValueSet>
  </contained>
  <identifier>
    <system value="urn:ietf:rfc:3986"/>
  </identifier>
  <status value="draft"/>
  <date value="2015-03-23T23:56:59+00:00"/>
  <publisher value="HL7 FHIR Project (Patient Care)"/>
  <group>
    <extension url="http://hl7.org/fhir/Profile/questionnaire-extensions#flyover">
      <valueString value="A request for a procedure to be performed. May be a proposal or an order."/>
    </extension>
    <linkId value="ProcedureRequest"/>
    <title value="A request for a procedure to be performed"/>
    <required value="true"/>
    <repeats value="false"/>
    <group>
      <extension url="http://hl7.org/fhir/Profile/questionnaire-extensions#flyover">
        <valueString value="The logical id of the resource, as used in the url for the resoure. Once assigned, this value never changes. The only time that a resource does not have an id is when it is being submitted to the server using a create operation. Bundles always have an id, though it is usually a generated UUID."/>
      </extension>
      <extension url="http://www.healthintersections.com.au/fhir/Profile/metadata#type">
        <valueString value="string"/>
      </extension>
      <linkId value="ProcedureRequest.id"/>
      <required value="false"/>
      <repeats value="true"/>
      <question>
        <linkId value="ProcedureRequest.id.value"/>
        <text value="Logical id of this artefact"/>
        <type value="string"/>
        <required value="false"/>
        <repeats value="false"/>
      </question>
    </group>
    <group>
      <extension url="http://hl7.org/fhir/Profile/questionnaire-extensions#flyover">
        <valueString value="The metadata about the resource. This is content that is maintained by the infrastructure. Changes to the content may not always be associated with version changes to the resource."/>
      </extension>
      <linkId value="ProcedureRequest.meta"/>
      <text value="Metadata about the resource"/>
      <required value="false"/>
      <repeats value="true"/>
    </group>
    <group>
      <extension url="http://hl7.org/fhir/Profile/questionnaire-extensions#flyover">
        <valueString value="A reference to a set of rules that were followed when the resource was constructed, and which must be understood when processing the content. Asserting this rule set restricts the content to be only understood by a limited set of trading partners. This inherently limits the usefulness of the data in the long term. However the existing health eco-system is highly fractured, and not yet ready to define, collect, and exchange data in a generally computable sense. Wherever possible, implementers and/or specification writers should avoid using this element as much as possible."/>
      </extension>
      <extension url="http://www.healthintersections.com.au/fhir/Profile/metadata#type">
        <valueString value="uri"/>
      </extension>
      <linkId value="ProcedureRequest.implicitRules"/>
      <required value="false"/>
      <repeats value="true"/>
      <question>
        <linkId value="ProcedureRequest.implicitRules.value"/>
        <text value="A set of rules under which this content was created"/>
        <type value="string"/>
        <required value="false"/>
        <repeats value="false"/>
      </question>
    </group>
    <group>
      <extension url="http://hl7.org/fhir/Profile/questionnaire-extensions#flyover">
        <valueString value="The base language in which the resource is written. Language is provided to support indexing and accessibility (typically, services such as text to speech use the language tag). The html language tag in the narrative applies  to the narrative. The language tag on the resource may be used to specify the language of other presentations generated from the data in the resource

Not all the content has to be in the base language. The Resource.language should not be assumed to apply to the narrative automatically. If a language is specified, it should it also be specified on the div element in the html (see rules in HTML5 for information about the relationship between xml:lang and the html lang attribute)."/>
      </extension>
      <extension url="http://www.healthintersections.com.au/fhir/Profile/metadata#type">
        <valueString value="code"/>
      </extension>
      <linkId value="ProcedureRequest.language"/>
      <required value="false"/>
      <repeats value="true"/>
      <question>
        <linkId value="ProcedureRequest.language.value"/>
        <text value="language"/>
        <type value="choice"/>
        <required value="false"/>
        <repeats value="false"/>
      </question>
    </group>
    <group>
      <extension url="http://hl7.org/fhir/Profile/questionnaire-extensions#flyover">
        <valueString value="A human-readable narrative that contains a summary of the resource, and may be used to represent the content of the resource to a human. The narrative need not encode all the structured data, but is required to contain sufficient detail to make it &quot;clinically safe&quot; for a human to just read the narrative. Resource definitions may define what content should be represented in the narrative to ensure clinical safety. Contained resources do not have narrative. Resources that are not contained SHOULD have a narrative."/>
      </extension>
      <linkId value="ProcedureRequest.text"/>
      <text value="Text summary of the resource, for human interpretation"/>
      <required value="false"/>
      <repeats value="true"/>
    </group>
    <group>
      <extension url="http://hl7.org/fhir/Profile/questionnaire-extensions#flyover">
        <valueString value="These resources do not have an independent existence apart from the resource that contains them - they cannot be identified independently, and nor can they have their own independent transaction scope. This should never be done when the content can be identified properly, as once identification is lost, it is extremely difficult (and context dependent) to restore it again."/>
      </extension>
      <linkId value="ProcedureRequest.contained"/>
      <text value="Contained, inline Resources"/>
      <required value="false"/>
      <repeats value="true"/>
    </group>
    <group>
      <extension url="http://hl7.org/fhir/Profile/questionnaire-extensions#flyover">
        <valueString value="Identifiers assigned to this order by the order or by the receiver."/>
      </extension>
      <extension url="http://www.healthintersections.com.au/fhir/Profile/metadata#type">
        <valueString value="Identifier"/>
      </extension>
      <linkId value="ProcedureRequest.identifier"/>
      <text value="Identifier"/>
      <required value="false"/>
      <repeats value="true"/>
      <question>
        <linkId value="ProcedureRequest.identifier.label"/>
        <text value="label:"/>
        <type value="string"/>
        <required value="false"/>
        <repeats value="false"/>
      </question>
      <question>
        <linkId value="ProcedureRequest.identifier.system"/>
        <text value="system:"/>
        <type value="string"/>
        <required value="false"/>
        <repeats value="false"/>
      </question>
      <question>
        <linkId value="ProcedureRequest.identifier.value"/>
        <text value="value:"/>
        <type value="string"/>
        <required value="false"/>
        <repeats value="false"/>
      </question>
    </group>
    <group>
      <extension url="http://hl7.org/fhir/Profile/questionnaire-extensions#flyover">
        <valueString value="The patient who will receive the procedure."/>
      </extension>
      <extension url="http://www.healthintersections.com.au/fhir/Profile/metadata#type">
        <valueString value="Reference"/>
      </extension>
      <linkId value="ProcedureRequest.subject"/>
      <required value="true"/>
      <repeats value="true"/>
      <question>
        <extension url="http://www.healthintersections.com.au/fhir/Profile/metadata#reference">
          <valueString value="/Patient?subject=$subj&amp;patient=$subj&amp;encounter=$encounter"/>
        </extension>
        <linkId value="ProcedureRequest.subject.value"/>
        <text value="Subject"/>
        <type value="reference"/>
        <required value="false"/>
        <repeats value="false"/>
      </question>
    </group>
    <group>
      <extension url="http://hl7.org/fhir/Profile/questionnaire-extensions#flyover">
        <valueString value="The specific procedure that is ordered. Use text if the exact nature of the procedure can&#39;t be coded."/>
      </extension>
      <extension url="http://www.healthintersections.com.au/fhir/Profile/metadata#type">
        <valueString value="CodeableConcept"/>
      </extension>
      <linkId value="ProcedureRequest.type"/>
      <text value="Procedure Type"/>
      <required value="true"/>
      <repeats value="true"/>
      <question>
        <linkId value="ProcedureRequest.type.coding"/>
        <text value="code:"/>
        <type value="open-choice"/>
        <required value="false"/>
        <repeats value="false"/>
      </question>
      <question>
        <linkId value="ProcedureRequest.type.text"/>
        <text value="text:"/>
        <type value="string"/>
        <required value="false"/>
        <repeats value="false"/>
      </question>
    </group>
    <group>
      <extension url="http://hl7.org/fhir/Profile/questionnaire-extensions#flyover">
        <valueString value="Indicates the site on the subject&#39;s body where the procedure should be performed ( i.e. the target site). Only used if not implicit in code found in ProcedureRequest.type."/>
      </extension>
      <linkId value="ProcedureRequest.bodySite[x]"/>
      <text value="Target body site"/>
      <required value="false"/>
      <repeats value="true"/>
      <question>
        <linkId value="ProcedureRequest.bodySite[x]._type"/>
        <text value="type"/>
        <type value="choice"/>
        <required value="false"/>
        <repeats value="false"/>
        <options>
          <reference value="#vs2"/>
        </options>
        <group>
          <extension url="http://www.healthintersections.com.au/fhir/Profile/metadata#type">
            <valueString value="CodeableConcept"/>
          </extension>
          <linkId value="ProcedureRequest.bodySite[x]._CodeableConcept"/>
          <text value="CodeableConcept"/>
          <question>
            <linkId value="ProcedureRequest.bodySite[x]._CodeableConcept.coding"/>
            <text value="code:"/>
            <type value="open-choice"/>
            <required value="false"/>
            <repeats value="false"/>
          </question>
          <question>
            <linkId value="ProcedureRequest.bodySite[x]._CodeableConcept.text"/>
            <text value="text:"/>
            <type value="string"/>
            <required value="false"/>
            <repeats value="false"/>
          </question>
        </group>
        <group>
          <extension url="http://www.healthintersections.com.au/fhir/Profile/metadata#type">
            <valueString value="Reference"/>
          </extension>
          <linkId value="ProcedureRequest.bodySite[x]._BodySite"/>
          <question>
            <extension url="http://www.healthintersections.com.au/fhir/Profile/metadata#reference">
              <valueString value="/BodySite?subject=$subj&amp;patient=$subj&amp;encounter=$encounter"/>
            </extension>
            <linkId value="ProcedureRequest.bodySite[x]._BodySite.value"/>
            <text value="BodySite"/>
            <type value="reference"/>
            <required value="false"/>
            <repeats value="false"/>
          </question>
        </group>
      </question>
    </group>
    <group>
      <extension url="http://hl7.org/fhir/Profile/questionnaire-extensions#flyover">
        <valueString value="The reason why the procedure is proposed or ordered. This procedure request may be motivated by a Condition for instance."/>
      </extension>
      <extension url="http://www.healthintersections.com.au/fhir/Profile/metadata#type">
        <valueString value="CodeableConcept"/>
      </extension>
      <linkId value="ProcedureRequest.indication"/>
      <text value="Indication"/>
      <required value="false"/>
      <repeats value="true"/>
      <question>
        <linkId value="ProcedureRequest.indication.coding"/>
        <text value="code:"/>
        <type value="open-choice"/>
        <required value="false"/>
        <repeats value="false"/>
      </question>
      <question>
        <linkId value="ProcedureRequest.indication.text"/>
        <text value="text:"/>
        <type value="string"/>
        <required value="false"/>
        <repeats value="false"/>
      </question>
    </group>
    <group>
      <extension url="http://hl7.org/fhir/Profile/questionnaire-extensions#flyover">
        <valueString value="The timing schedule for the proposed or ordered procedure. The Schedule data type allows many different expressions, for example. &quot;Every 8 hours&quot;; &quot;Three times a day&quot;; &quot;1/2 an hour before breakfast for 10 days from 23-Dec 2011:&quot;; &quot;15 Oct 2013, 17 Oct 2013 and 1 Nov 2013&quot;."/>
      </extension>
      <linkId value="ProcedureRequest.timing[x]"/>
      <text value="Timing"/>
      <required value="false"/>
      <repeats value="true"/>
      <question>
        <linkId value="ProcedureRequest.timing[x]._type"/>
        <text value="type"/>
        <type value="choice"/>
        <required value="false"/>
        <repeats value="false"/>
        <options>
          <reference value="#vs3"/>
        </options>
        <group>
          <extension url="http://www.healthintersections.com.au/fhir/Profile/metadata#type">
            <valueString value="datetime"/>
          </extension>
          <linkId value="ProcedureRequest.timing[x]._dateTime"/>
          <question>
            <linkId value="ProcedureRequest.timing[x]._dateTime.value"/>
            <text value="dateTime"/>
            <type value="dateTime"/>
            <required value="false"/>
            <repeats value="false"/>
          </question>
        </group>
        <group>
          <extension url="http://www.healthintersections.com.au/fhir/Profile/metadata#type">
            <valueString value="Period"/>
          </extension>
          <linkId value="ProcedureRequest.timing[x]._Period"/>
          <text value="Period"/>
          <question>
            <linkId value="ProcedureRequest.timing[x]._Period.low"/>
            <text value="start:"/>
            <type value="dateTime"/>
            <required value="false"/>
            <repeats value="false"/>
          </question>
          <question>
            <linkId value="ProcedureRequest.timing[x]._Period.end"/>
            <text value="end:"/>
            <type value="dateTime"/>
            <required value="false"/>
            <repeats value="false"/>
          </question>
        </group>
        <group>
          <extension url="http://www.healthintersections.com.au/fhir/Profile/metadata#type">
            <valueString value="Schedule"/>
          </extension>
          <linkId value="ProcedureRequest.timing[x]._Timing"/>
          <text value="Timing"/>
        </group>
      </question>
    </group>
    <group>
      <extension url="http://hl7.org/fhir/Profile/questionnaire-extensions#flyover">
        <valueString value="The encounter within which the procedure proposal or request was created."/>
      </extension>
      <extension url="http://www.healthintersections.com.au/fhir/Profile/metadata#type">
        <valueString value="Reference"/>
      </extension>
      <linkId value="ProcedureRequest.encounter"/>
      <required value="false"/>
      <repeats value="true"/>
      <question>
        <extension url="http://www.healthintersections.com.au/fhir/Profile/metadata#reference">
          <valueString value="/Encounter?subject=$subj&amp;patient=$subj&amp;encounter=$encounter"/>
        </extension>
        <linkId value="ProcedureRequest.encounter.value"/>
        <text value="Encounter"/>
        <type value="reference"/>
        <required value="false"/>
        <repeats value="false"/>
      </question>
    </group>
    <group>
      <extension url="http://hl7.org/fhir/Profile/questionnaire-extensions#flyover">
        <valueString value="E.g. surgeon, anaethetist, endoscopist."/>
      </extension>
      <linkId value="ProcedureRequest.performer"/>
      <text value="Performer"/>
      <required value="false"/>
      <repeats value="true"/>
      <question>
        <linkId value="ProcedureRequest.performer._type"/>
        <text value="type"/>
        <type value="choice"/>
        <required value="false"/>
        <repeats value="false"/>
        <options>
          <reference value="#vs4"/>
        </options>
        <group>
          <extension url="http://www.healthintersections.com.au/fhir/Profile/metadata#type">
            <valueString value="Reference"/>
          </extension>
          <linkId value="ProcedureRequest.performer._Practitioner"/>
          <question>
            <extension url="http://www.healthintersections.com.au/fhir/Profile/metadata#reference">
              <valueString value="/Practitioner?subject=$subj&amp;patient=$subj&amp;encounter=$encounter"/>
            </extension>
            <linkId value="ProcedureRequest.performer._Practitioner.value"/>
            <text value="Practitioner"/>
            <type value="reference"/>
            <required value="false"/>
            <repeats value="false"/>
          </question>
        </group>
        <group>
          <extension url="http://www.healthintersections.com.au/fhir/Profile/metadata#type">
            <valueString value="Reference"/>
          </extension>
          <linkId value="ProcedureRequest.performer._Organization"/>
          <question>
            <extension url="http://www.healthintersections.com.au/fhir/Profile/metadata#reference">
              <valueString value="/Organization?subject=$subj&amp;patient=$subj&amp;encounter=$encounter"/>
            </extension>
            <linkId value="ProcedureRequest.performer._Organization.value"/>
            <text value="Organization"/>
            <type value="reference"/>
            <required value="false"/>
            <repeats value="false"/>
          </question>
        </group>
        <group>
          <extension url="http://www.healthintersections.com.au/fhir/Profile/metadata#type">
            <valueString value="Reference"/>
          </extension>
          <linkId value="ProcedureRequest.performer._Patient"/>
          <question>
            <extension url="http://www.healthintersections.com.au/fhir/Profile/metadata#reference">
              <valueString value="/Patient?subject=$subj&amp;patient=$subj&amp;encounter=$encounter"/>
            </extension>
            <linkId value="ProcedureRequest.performer._Patient.value"/>
            <text value="Patient"/>
            <type value="reference"/>
            <required value="false"/>
            <repeats value="false"/>
          </question>
        </group>
        <group>
          <extension url="http://www.healthintersections.com.au/fhir/Profile/metadata#type">
            <valueString value="Reference"/>
          </extension>
          <linkId value="ProcedureRequest.performer._RelatedPerson"/>
          <question>
            <extension url="http://www.healthintersections.com.au/fhir/Profile/metadata#reference">
              <valueString value="/RelatedPerson?subject=$subj&amp;patient=$subj&amp;encounter=$encounter"/>
            </extension>
            <linkId value="ProcedureRequest.performer._RelatedPerson.value"/>
            <text value="RelatedPerson"/>
            <type value="reference"/>
            <required value="false"/>
            <repeats value="false"/>
          </question>
        </group>
      </question>
    </group>
    <group>
      <extension url="http://hl7.org/fhir/Profile/questionnaire-extensions#flyover">
        <valueString value="The status of the order."/>
      </extension>
      <extension url="http://www.healthintersections.com.au/fhir/Profile/metadata#type">
        <valueString value="code"/>
      </extension>
      <linkId value="ProcedureRequest.status"/>
      <required value="false"/>
      <repeats value="true"/>
      <question>
        <linkId value="ProcedureRequest.status.value"/>
        <text value="status"/>
        <type value="choice"/>
        <required value="false"/>
        <repeats value="false"/>
      </question>
    </group>
    <group>
      <extension url="http://hl7.org/fhir/Profile/questionnaire-extensions#flyover">
        <valueString value="Any other notes associated with this proposal or order - e.g., provider instructions."/>
      </extension>
      <extension url="http://www.healthintersections.com.au/fhir/Profile/metadata#type">
        <valueString value="string"/>
      </extension>
      <linkId value="ProcedureRequest.notes"/>
      <required value="false"/>
      <repeats value="true"/>
      <question>
        <linkId value="ProcedureRequest.notes.value"/>
        <text value="Notes"/>
        <type value="string"/>
        <required value="false"/>
        <repeats value="false"/>
      </question>
    </group>
    <group>
      <extension url="http://hl7.org/fhir/Profile/questionnaire-extensions#flyover">
        <valueString value="If a CodeableConcept is present, it indicates the pre-condition for performing the procedure."/>
      </extension>
      <linkId value="ProcedureRequest.asNeeded[x]"/>
      <text value="PRN"/>
      <required value="false"/>
      <repeats value="true"/>
      <question>
        <linkId value="ProcedureRequest.asNeeded[x]._type"/>
        <text value="type"/>
        <type value="choice"/>
        <required value="false"/>
        <repeats value="false"/>
        <options>
          <reference value="#vs5"/>
        </options>
        <group>
          <extension url="http://www.healthintersections.com.au/fhir/Profile/metadata#type">
            <valueString value="boolean"/>
          </extension>
          <linkId value="ProcedureRequest.asNeeded[x]._boolean"/>
          <question>
            <linkId value="ProcedureRequest.asNeeded[x]._boolean.value"/>
            <text value="boolean"/>
            <type value="boolean"/>
            <required value="false"/>
            <repeats value="false"/>
          </question>
        </group>
        <group>
          <extension url="http://www.healthintersections.com.au/fhir/Profile/metadata#type">
            <valueString value="CodeableConcept"/>
          </extension>
          <linkId value="ProcedureRequest.asNeeded[x]._CodeableConcept"/>
          <text value="CodeableConcept"/>
          <question>
            <linkId value="ProcedureRequest.asNeeded[x]._CodeableConcept.coding"/>
            <text value="code:"/>
            <type value="open-choice"/>
            <required value="false"/>
            <repeats value="false"/>
          </question>
          <question>
            <linkId value="ProcedureRequest.asNeeded[x]._CodeableConcept.text"/>
            <text value="text:"/>
            <type value="string"/>
            <required value="false"/>
            <repeats value="false"/>
          </question>
        </group>
      </question>
    </group>
    <group>
      <extension url="http://hl7.org/fhir/Profile/questionnaire-extensions#flyover">
        <valueString value="The time when the request was made."/>
      </extension>
      <extension url="http://www.healthintersections.com.au/fhir/Profile/metadata#type">
        <valueString value="datetime"/>
      </extension>
      <linkId value="ProcedureRequest.orderedOn"/>
      <required value="false"/>
      <repeats value="true"/>
      <question>
        <linkId value="ProcedureRequest.orderedOn.value"/>
        <text value="When Requested"/>
        <type value="dateTime"/>
        <required value="false"/>
        <repeats value="false"/>
      </question>
    </group>
    <group>
      <extension url="http://hl7.org/fhir/Profile/questionnaire-extensions#flyover">
        <valueString value="The healthcare professional responsible for proposing or ordering the procedure."/>
      </extension>
      <linkId value="ProcedureRequest.orderer"/>
      <text value="Ordering Party"/>
      <required value="false"/>
      <repeats value="true"/>
      <question>
        <linkId value="ProcedureRequest.orderer._type"/>
        <text value="type"/>
        <type value="choice"/>
        <required value="false"/>
        <repeats value="false"/>
        <options>
          <reference value="#vs6"/>
        </options>
        <group>
          <extension url="http://www.healthintersections.com.au/fhir/Profile/metadata#type">
            <valueString value="Reference"/>
          </extension>
          <linkId value="ProcedureRequest.orderer._Practitioner"/>
          <question>
            <extension url="http://www.healthintersections.com.au/fhir/Profile/metadata#reference">
              <valueString value="/Practitioner?subject=$subj&amp;patient=$subj&amp;encounter=$encounter"/>
            </extension>
            <linkId value="ProcedureRequest.orderer._Practitioner.value"/>
            <text value="Practitioner"/>
            <type value="reference"/>
            <required value="false"/>
            <repeats value="false"/>
          </question>
        </group>
        <group>
          <extension url="http://www.healthintersections.com.au/fhir/Profile/metadata#type">
            <valueString value="Reference"/>
          </extension>
          <linkId value="ProcedureRequest.orderer._Patient"/>
          <question>
            <extension url="http://www.healthintersections.com.au/fhir/Profile/metadata#reference">
              <valueString value="/Patient?subject=$subj&amp;patient=$subj&amp;encounter=$encounter"/>
            </extension>
            <linkId value="ProcedureRequest.orderer._Patient.value"/>
            <text value="Patient"/>
            <type value="reference"/>
            <required value="false"/>
            <repeats value="false"/>
          </question>
        </group>
        <group>
          <extension url="http://www.healthintersections.com.au/fhir/Profile/metadata#type">
            <valueString value="Reference"/>
          </extension>
          <linkId value="ProcedureRequest.orderer._RelatedPerson"/>
          <question>
            <extension url="http://www.healthintersections.com.au/fhir/Profile/metadata#reference">
              <valueString value="/RelatedPerson?subject=$subj&amp;patient=$subj&amp;encounter=$encounter"/>
            </extension>
            <linkId value="ProcedureRequest.orderer._RelatedPerson.value"/>
            <text value="RelatedPerson"/>
            <type value="reference"/>
            <required value="false"/>
            <repeats value="false"/>
          </question>
        </group>
        <group>
          <extension url="http://www.healthintersections.com.au/fhir/Profile/metadata#type">
            <valueString value="Reference"/>
          </extension>
          <linkId value="ProcedureRequest.orderer._Device"/>
          <question>
            <extension url="http://www.healthintersections.com.au/fhir/Profile/metadata#reference">
              <valueString value="/Device?subject=$subj&amp;patient=$subj&amp;encounter=$encounter"/>
            </extension>
            <linkId value="ProcedureRequest.orderer._Device.value"/>
            <text value="Device"/>
            <type value="reference"/>
            <required value="false"/>
            <repeats value="false"/>
          </question>
        </group>
      </question>
    </group>
    <group>
      <extension url="http://hl7.org/fhir/Profile/questionnaire-extensions#flyover">
        <valueString value="The clinical priority associated with this order."/>
      </extension>
      <extension url="http://www.healthintersections.com.au/fhir/Profile/metadata#type">
        <valueString value="code"/>
      </extension>
      <linkId value="ProcedureRequest.priority"/>
      <required value="false"/>
      <repeats value="true"/>
      <question>
        <linkId value="ProcedureRequest.priority.value"/>
        <text value="priority"/>
        <type value="choice"/>
        <required value="false"/>
        <repeats value="false"/>
      </question>
    </group>
  </group>
</Questionnaire>